{
  "authenticity": null,
  "brand": null,
  "condition": "New",
  "description": "\u0d85\u0db4 \u0dc0\u0dd2\u0dc3\u0dd2\u0db1\u0dca \u0dc3\u0db8\u0dca\u0db4\u0dd4\u0dbb\u0dca\u0dab \u0db4\u0daf\u0dca\u0db0\u0dad\u0dd2\u0dba \u0dc0\u0dd2\u0d9a\u0dd2\u0dab\u0dd3\u0db8 \u0db4\u0db8\u0dab\u0d9a\u0dca \u0dc3\u0dd2\u0daf\u0dd4\u0d9a\u0dbb\u0dba\u0dd2. ",
  "edition": null,
  "features": null,
  "location": "Kiribathgoda, Gampaha",
  "model": null,
  "posted_by": "For sale by Eco Digital (Pvt) Ltd ",
  "posted_time": "19 Jun  2:12 pm",
  "price": "33,000",
  "title": "CCTV from Vietnam"
}